funding_rates_mcp/__init__.py
funding_rates_mcp/cli.py
funding_rates_mcp-0.1.0.dist-info/METADATA
funding_rates_mcp-0.1.0.dist-info/WHEEL
funding_rates_mcp-0.1.0.dist-info/entry_points.txt
funding_rates_mcp-0.1.0.dist-info/licenses/LICENSE
funding_rates_mcp-0.1.0.dist-info/RECORD
