Metadata-Version: 2.4
Name: funding-rates-mcp
Version: 0.1.0
Summary: An MCP server that provides real-time funding rate data across major crypto exchanges, enabling agents to detect arbitrage opportunities. 
License-File: LICENSE
Requires-Python: >=3.10
Requires-Dist: cachetools>=5.5.2
Requires-Dist: ccxt>=4.4.75
Requires-Dist: dotenv>=0.9.9
Requires-Dist: mcp[cli]>=1.6.0
Requires-Dist: pandas>=2.2.3
Requires-Dist: tabulate>=0.9.0
